{
    "q1": "궁금한게 있으면 바로바로 물어본다.",
    "q2": "일을 열심히 해서 하나라도 더 챙겨주고 싶다.",
    "q3": "여러 가지 의견을 잘 내는 편이다.",
    "q4": "동료의 일을 도와주는 것이라면 개의치 않고 도와주는 편이다.",
    "q5": "대화할 때 상대방의 말을 항상 잘 듣고 의견을 존중한다.",
    "q6": "도와줄 일이 없는지 먼저 물어보는 편이다.",
    "q7": "시간 약속을 잘 지키는 편이다.",
    "q8": "항상 용모가 단정하며 손님들에게 친절한 편이다.",
    "q9": "시키는 일은 미루지 않고 바로 시작한다.",
    "q10": "맡은 업무는 끝까지 하는 편이다.",
    "q11": "알바를 그만 두기 전 미리 고지하여 업무에 지장이 없게 하였다.",
    "q12": "실수가 발생했을 때 일의 수습을 깔끔하게 잘했다.",
    "q13": "정해진 메뉴얼 대로만 처리하는 일보다는 끊임없는 변화를 추구하는 일을 더 선호한다.",
    "q14": "다른 사람들이 쉽게 생각하지 못하는 독특한 방식으로 일하는 편이다.",
    "q15": "더 효율적인 방법으로 일하는 것을 제시한 적이 있다.",
    "q16": "함께 일하는 사람들을 활기차게 만드는 편이다.",
    "q17": "본인이 아닌 다른 사람의 실수를 같이 책임진 적이 있다.",
    "q18": "성격이 우둔하고 중심이 잡혀 주변사람들이 잘 따랐다."
}